neumai_tools/DatasetEvaluation/Dataset.py
neumai_tools/DatasetEvaluation/DatasetUtils.py
neumai_tools/DatasetEvaluation/Evaluation.py
neumai_tools/DatasetEvaluation/__init__.py
neumai_tools/InteropHelpers/DocumentTransformer.py
neumai_tools/InteropHelpers/__init__.py
neumai_tools/PipelineCollection/PipelineCollection.py
neumai_tools/PipelineCollection/__init__.py
neumai_tools/SemanticHelpers/__init__.py
neumai_tools/SemanticHelpers/file_prep.py
neumai_tools/SemanticHelpers/semantic_chunking.py
neumai_tools/SemanticHelpers/semantic_metadata.py
neumai_tools/SemanticHelpers/semantic_retrieval.py
neumai_tools/__init__.py
neumai_tools-0.0.19.dist-info/METADATA
neumai_tools-0.0.19.dist-info/WHEEL
neumai_tools-0.0.19.dist-info/RECORD
