Metadata-Version: 2.1
Name: neumai-tools
Version: 0.0.19
Summary: Package containing helper tools for Neum AI.
Home-page: https://neum.ai
License: MIT
Keywords: neumai,ai tools,data tools
Author: David de Matheu
Author-email: david@tryneum.com
Requires-Python: >=3.10,<4.0
Classifier: License :: OSI Approved :: MIT License
Classifier: Programming Language :: Python :: 3
Classifier: Programming Language :: Python :: 3.10
Classifier: Programming Language :: Python :: 3.11
Requires-Dist: langchain (==0.0.335)
Requires-Dist: llama-index (==0.9.3)
Requires-Dist: neumai (>=0.0.34)
Requires-Dist: openai (==1.2.4)
Requires-Dist: pandas (==2.1.0)
Requires-Dist: tiktoken (==0.4.0)
Project-URL: Repository, https://github.com/NeumTry/neum-tools
